setup.py
django_kvstore/__init__.py
django_kvstore/models.py
django_kvstore.egg-info/PKG-INFO
django_kvstore.egg-info/SOURCES.txt
django_kvstore.egg-info/dependency_links.txt
django_kvstore.egg-info/requires.txt
django_kvstore.egg-info/top_level.txt
django_kvstore.egg-info/zip-safe
django_kvstore/backends/__init__.py
django_kvstore/backends/base.py
django_kvstore/backends/db.py
django_kvstore/backends/googleappengine.py
django_kvstore/backends/locmem.py
django_kvstore/backends/memcached.py
django_kvstore/backends/sdb.py
django_kvstore/backends/tokyotyrant.py