Metadata-Version: 1.1
Name: django-kvstore
Version: 1.0
Summary: An extensible key-value store backend for Django applications.
Home-page: http://github.com/sixapart/django-kvstore
Author: Six Apart Ltd.
Author-email: python@sixapart.com
License: UNKNOWN
Platform: UNKNOWN
Classifier: Development Status :: 4 - Beta
Classifier: Environment :: Console
Classifier: Environment :: Web Environment
Classifier: Framework :: Django
Classifier: Intended Audience :: Developers
Classifier: License :: OSI Approved :: BSD License
Classifier: Operating System :: MacOS :: MacOS X
Classifier: Operating System :: POSIX
Classifier: Programming Language :: Python
Classifier: Topic :: Internet :: WWW/HTTP
Requires: Django(>=1.1.1)
Provides: django_kvstore
